setup.py
moveit/__init__.py
moveit/flow.py
moveit/moveit.py
moveit.egg-info/PKG-INFO
moveit.egg-info/SOURCES.txt
moveit.egg-info/dependency_links.txt
moveit.egg-info/entry_points.txt
moveit.egg-info/requires.txt
moveit.egg-info/top_level.txt