Metadata-Version: 1.1
Name: moveit
Version: 0.7.5
Summary: ns_server master events analyzer
Home-page: UNKNOWN
Author: Pavel Paulau
Author-email: pavel.paulau@gmail.com
License: UNKNOWN
Platform: UNKNOWN
Classifier: Programming Language :: Python
Classifier: Programming Language :: Python :: 2.7
Classifier: Programming Language :: Python :: 3.3
Classifier: Development Status :: 5 - Production/Stable
Classifier: License :: OSI Approved :: Apache Software License
Classifier: Operating System :: OS Independent
Classifier: Topic :: Software Development :: Libraries :: Python Modules
